sc_weekly_points/__init__.py
sc_weekly_points/main.py
sc_weekly_points/utils.py
sc_weekly_points/analyzer/__init__.py
sc_weekly_points/analyzer/points_analyzer.py
sc_weekly_points/tests/__init__.py
sc_weekly_points/tests/sample_config/production.yml
sc_weekly_points/tests/sample_config/模板.xlsx
sc_weekly_points-0.0.4.dist-info/LICENSE
sc_weekly_points-0.0.4.dist-info/METADATA
sc_weekly_points-0.0.4.dist-info/WHEEL
sc_weekly_points-0.0.4.dist-info/entry_points.txt
sc_weekly_points-0.0.4.dist-info/top_level.txt
sc_weekly_points-0.0.4.dist-info/RECORD
